qandle/__init__.py
qandle/config.py
qandle/convolution.py
qandle/drawer.py
qandle/embeddings.py
qandle/errors.py
qandle/measurements.py
qandle/operators.py
qandle/qasm.py
qandle/qcircuit.py
qandle/utils.py
qandle/ansaetze/__init__.py
qandle/ansaetze/ansatz.py
qandle/ansaetze/specialunitary.py
qandle/ansaetze/stronglyentangling.py
qandle/ansaetze/stronglyentangling_budget.py
qandle/ansaetze/twolocal.py
qandle/splitter/__init__.py
qandle/splitter/grouping.py
qandle/splitter/main.py
qandle/test/__init__.py
qandle/test/check_qasm.py
qandle/test/test_ansaetze.py
qandle/test/test_convolution.py
qandle/test/test_embeddings.py
qandle/test/test_measurements.py
qandle/test/test_operators.py
qandle/test/test_splitter.py
qandle-0.1.12.dist-info/licenses/LICENSE
qandle-0.1.12.dist-info/METADATA
qandle-0.1.12.dist-info/WHEEL
qandle-0.1.12.dist-info/top_level.txt
qandle-0.1.12.dist-info/RECORD
