Metadata-Version: 2.4
Name: qandle
Version: 0.1.12
Summary: QANDLE is a fast and simple quantum state-vector simulator for hybrid machine learning using the PyTorch library.
Author-email: Gerhard Stenzel <gerhard.stenzel@ifi.lmu.de>
License-Expression: MIT
Project-URL: documentation, https://gstenzel.github.io/qandle/
Project-URL: repository, https://github.com/gstenzel/qandle/
Classifier: Programming Language :: Python :: 3
Classifier: Operating System :: OS Independent
Classifier: Development Status :: 4 - Beta
Classifier: Environment :: GPU :: NVIDIA CUDA
Classifier: Intended Audience :: Science/Research
Classifier: Topic :: Scientific/Engineering :: Artificial Intelligence
Classifier: Programming Language :: Python
Requires-Python: >=3.12
License-File: LICENSE
Requires-Dist: torch>=2
Requires-Dist: qW-Map>=0.1
Requires-Dist: networkx>=3
Requires-Dist: einops>=0.8
Requires-Dist: openqasm3[parser]>=1
Provides-Extra: dev
Requires-Dist: PennyLane>=0.33; extra == "dev"
Requires-Dist: pytest>=7.4; extra == "dev"
Requires-Dist: pytest-cov>=5.0.0; extra == "dev"
Requires-Dist: snakeviz>=2.2; extra == "dev"
Requires-Dist: sphinx>=7.4.7; extra == "dev"
Requires-Dist: myst-nb>=1.1.1; extra == "dev"
Requires-Dist: sphinx-rtd-theme>=2.0.0; extra == "dev"
Requires-Dist: ruff>=0.5.5; extra == "dev"
Dynamic: license-file
